{
  "products": [
    {
      "id": 1,
      "title": "Bryggkaffe",
      "description": "Bryggd på månadens bönor",
      "price": 49
    },
    {
      "id": 2,
      "title": "Caffè Doppio",
      "description": "Bryggd på månadens bönor",
      "price": 49
    },
    {
      "id": 3,
      "title": "Cappuccino",
      "description": "Bryggd på månadens bönor",
      "price": 49
    },
    {
      "id": 4,
      "title": "Latte Macchiato",
      "description": "Bryggd på månadens bönor",
      "price": 49
    },
    {
      "id": 5,
      "title": "Kaffe Latte",
      "description": "Bryggd på månadens bönor",
      "price": 49
    },
    {
      "id": 6,
      "title": "Cortado",
      "description": "Bryggd på månadens bönor",
      "price": 39
    }
  ]
}
